pdf_docx_pic/__init__.py
pdf_docx_pic/main.py
pdf_docx_pic-5.24.12.8.2.dist-info/METADATA
pdf_docx_pic-5.24.12.8.2.dist-info/WHEEL
pdf_docx_pic-5.24.12.8.2.dist-info/top_level.txt
pdf_docx_pic-5.24.12.8.2.dist-info/RECORD
